{
    "scraped_time": "2026-04-04 08:37:16",
    "videos": [
        {
            "video_id": "D54StAZFUrc",
            "title": "AKMU - '소문의 낙원 (Paradise of Rumors)' M/V",
            "channel_name": "AKMU",
            "category": "Music",
            "duration": "3:38",
            "view_count": "1672568",
            "thumbnail_url": "https://i.ytimg.com/vi/D54StAZFUrc/hqdefault.jpg"
        },
        {
            "video_id": "uK09QeHT2g0",
            "title": "마지막 영상 낋여왔습니다. ≪스파이더맨: 브랜드뉴데이≫ 티저 예고편 분석 3탄 & 떡밥 및 루머 총정리",
            "channel_name": "무비띵크_Movie Think",
            "category": "Film & Animation",
            "duration": "12:31",
            "view_count": "180067",
            "thumbnail_url": "https://i.ytimg.com/vi/uK09QeHT2g0/hqdefault.jpg"
        },
        {
            "video_id": "Yp9IKCCvV1E",
            "title": "[ 똘끼 리니지클래식 ep.11 ] 마법사 자동 그리고 대기열...",
            "channel_name": "똘끼100%",
            "category": "Gaming",
            "duration": "6:44:41",
            "view_count": "221428",
            "thumbnail_url": "https://i.ytimg.com/vi/Yp9IKCCvV1E/hqdefault.jpg"
        },
        {
            "video_id": "_gyultVTesk",
            "title": "BTS (방탄소년단) '2.0' Official MV",
            "channel_name": "HYBE LABELS",
            "category": "Music",
            "duration": "3:55",
            "view_count": "21022038",
            "thumbnail_url": "https://i.ytimg.com/vi/_gyultVTesk/hqdefault.jpg"
        },
        {
            "video_id": "oTbFkKDzstI",
            "title": "“한국에게 완전히 지배당했다” 1위 일본영화 예고편 공개되자 방송중단 / “생각보다 훨씬 심각한 상황”",
            "channel_name": "꿀튜브",
            "category": "News & Politics",
            "duration": "8:39",
            "view_count": "32636",
            "thumbnail_url": "https://i.ytimg.com/vi/oTbFkKDzstI/hqdefault.jpg"
        },
        {
            "video_id": "taZl_NyreGI",
            "title": "같은팀에 넣어놨더니 오더부터 밸붕 수준인 피넛&클리드",
            "channel_name": "튜브김민교",
            "category": "Gaming",
            "duration": "33:49",
            "view_count": "193475",
            "thumbnail_url": "https://i.ytimg.com/vi/taZl_NyreGI/hqdefault.jpg"
        },
        {
            "video_id": "lh7yT1PF2Y4",
            "title": "T.O.P - \"DESPERADO\" MV",
            "channel_name": "T.O.P",
            "category": "Music",
            "duration": "3:38",
            "view_count": "1063516",
            "thumbnail_url": "https://i.ytimg.com/vi/lh7yT1PF2Y4/hqdefault.jpg"
        },
        {
            "video_id": "Wg5SBEPER-4",
            "title": "\"캬.. 이러면 재밌지💥\" ≪슈퍼걸≫ 2차 예고편 분석 리뷰",
            "channel_name": "기묘한 케이지",
            "category": "Film & Animation",
            "duration": "11:14",
            "view_count": "64346",
            "thumbnail_url": "https://i.ytimg.com/vi/Wg5SBEPER-4/hqdefault.jpg"
        },
        {
            "video_id": "DsKnaCIAYNg",
            "title": "GEN vs KT - BFX vs BRO | 2026 LCK",
            "channel_name": "LCK Global",
            "category": "Gaming",
            "duration": "5:48:41",
            "view_count": "471346",
            "thumbnail_url": "https://i.ytimg.com/vi/DsKnaCIAYNg/hqdefault.jpg"
        },
        {
            "video_id": "_9g-EV3u-o8",
            "title": "PARK HYO SHIN (박효신) - ‘AE’ Official MV",
            "channel_name": "박효신 PARK HYO SHIN",
            "category": "Music",
            "duration": "5:23",
            "view_count": "171986",
            "thumbnail_url": "https://i.ytimg.com/vi/_9g-EV3u-o8/hqdefault.jpg"
        },
        {
            "video_id": "4zm6hEr9LWc",
            "title": "임영웅 출연 영화 예고편 전격 공개, 이 사람 등장에 깜짝??",
            "channel_name": "젊은할배 59TV",
            "category": "Entertainment",
            "duration": "4:30",
            "view_count": "8182",
            "thumbnail_url": "https://i.ytimg.com/vi/4zm6hEr9LWc/hqdefault.jpg"
        },
        {
            "video_id": "dynQbVp1g30",
            "title": "GEN vs GE / T1 vs VL - VCT 퍼시픽 - 스테이지 1 - 그룹 스테이지 -  Day 1",
            "channel_name": "발로란트 챔피언스 투어",
            "category": "Gaming",
            "duration": "5:21:27",
            "view_count": "180368",
            "thumbnail_url": "https://i.ytimg.com/vi/dynQbVp1g30/hqdefault.jpg"
        },
        {
            "video_id": "PYpOJyl3Sbg",
            "title": "GAME OVER ?",
            "channel_name": "HANRORO - Topic",
            "category": "Music",
            "duration": "3:17",
            "view_count": "317468",
            "thumbnail_url": "https://i.ytimg.com/vi/PYpOJyl3Sbg/hqdefault.jpg"
        },
        {
            "video_id": "HZ_tOMIyRXw",
            "title": "방 들어가자마자 X밥 취급하며 무시하는 상대에게... 곧바로 22초 일꾼러쉬로 참교육 시작ㅋㅋ",
            "channel_name": "[ALTUBE] 김성현TV",
            "category": "Gaming",
            "duration": "35:26",
            "view_count": "91741",
            "thumbnail_url": "https://i.ytimg.com/vi/HZ_tOMIyRXw/hqdefault.jpg"
        },
        {
            "video_id": "eMouvDpiEVU",
            "title": "R.I.L + King′s gambit (Prod. by ZICO, Crush)",
            "channel_name": "HAON - Topic",
            "category": "Music",
            "duration": "5:26",
            "view_count": "158271",
            "thumbnail_url": "https://i.ytimg.com/vi/eMouvDpiEVU/hqdefault.jpg"
        },
        {
            "video_id": "8dPbTMV591w",
            "title": "마인크래프트에서 가장 위험한 비밀 모두 모으기",
            "channel_name": "프뚜",
            "category": "Gaming",
            "duration": "35:26",
            "view_count": "107588",
            "thumbnail_url": "https://i.ytimg.com/vi/8dPbTMV591w/hqdefault.jpg"
        },
        {
            "video_id": "K-F7906Jq9U",
            "title": "PLAVE '흥흥흥 (feat. SOLE)' Special Video",
            "channel_name": "PLAVE 플레이브",
            "category": "Entertainment",
            "duration": "3:08",
            "view_count": "2568910",
            "thumbnail_url": "https://i.ytimg.com/vi/K-F7906Jq9U/hqdefault.jpg"
        },
        {
            "video_id": "Lf1f6TydRsU",
            "title": "리니지클래식 쇼크스턴 ㅋㅋㅋㅋㅋㅋㅋㅋㅋㅋㅋㅋㅋㅋㅋ",
            "channel_name": "이문주",
            "category": "Gaming",
            "duration": "3:54:23",
            "view_count": "65329",
            "thumbnail_url": "https://i.ytimg.com/vi/Lf1f6TydRsU/hqdefault.jpg"
        },
        {
            "video_id": "wZz73re_ITk",
            "title": "NOW IM YOUNG (Prod. by Hukky Shibaseki)",
            "channel_name": "nowimyoung - Topic",
            "category": "Music",
            "duration": "3:35",
            "view_count": "89784",
            "thumbnail_url": "https://i.ytimg.com/vi/wZz73re_ITk/hqdefault.jpg"
        },
        {
            "video_id": "8GU1Olt1lWk",
            "title": "마크판 서유기: 현명한 선택으로 경전의 주인이 되어라",
            "channel_name": "잠뜰 TV",
            "category": "Gaming",
            "duration": "40:06",
            "view_count": "116344",
            "thumbnail_url": "https://i.ytimg.com/vi/8GU1Olt1lWk/hqdefault.jpg"
        },
        {
            "video_id": "s0-m0gHYTjA",
            "title": "New New (Prod. by GroovyRoom)",
            "channel_name": "Tray B - Topic",
            "category": "Music",
            "duration": "3:43",
            "view_count": "52849",
            "thumbnail_url": "https://i.ytimg.com/vi/s0-m0gHYTjA/hqdefault.jpg"
        },
        {
            "video_id": "n_M8_8wVOM4",
            "title": "오랜만에 탑 출격했다가 골드 이렐리아한테 1렙부터 CS 통제 당하고 오열하는 이상호..!",
            "channel_name": "이상호",
            "category": "Gaming",
            "duration": "22:30",
            "view_count": "202584",
            "thumbnail_url": "https://i.ytimg.com/vi/n_M8_8wVOM4/hqdefault.jpg"
        },
        {
            "video_id": "om6HdemgTKQ",
            "title": "BTS (방탄소년단) 'SWIM' Live Clip II. (Swimming Pool ver.)",
            "channel_name": "BANGTANTV",
            "category": "Music",
            "duration": "3:07",
            "view_count": "7032755",
            "thumbnail_url": "https://i.ytimg.com/vi/om6HdemgTKQ/hqdefault.jpg"
        },
        {
            "video_id": "zH2MbqbmxaU",
            "title": "[Limbus Company - Teaser] Chapter 9.5 - 타래 엮기 / 縒り合せ / Twining Threads",
            "channel_name": "ProjectMoon Official",
            "category": "Gaming",
            "duration": "1:02",
            "view_count": "296974",
            "thumbnail_url": "https://i.ytimg.com/vi/zH2MbqbmxaU/hqdefault.jpg"
        },
        {
            "video_id": "JunGeblTQ4E",
            "title": "GR8EST (Prod. by APRO)",
            "channel_name": "Untell - Topic",
            "category": "Music",
            "duration": "4:43",
            "view_count": "58157",
            "thumbnail_url": "https://i.ytimg.com/vi/JunGeblTQ4E/hqdefault.jpg"
        },
        {
            "video_id": "plBayfCW4Eg",
            "title": "장사꾼에게 팔려버린 1위 스타라이트",
            "channel_name": "레고77",
            "category": "Gaming",
            "duration": "11:28",
            "view_count": "169155",
            "thumbnail_url": "https://i.ytimg.com/vi/plBayfCW4Eg/hqdefault.jpg"
        },
        {
            "video_id": "e6CGI5JOZ7g",
            "title": "임영웅 [이제 나만 믿어요] Jazz Ver. @IM HERO TOUR 2",
            "channel_name": "임영웅",
            "category": "Music",
            "duration": "4:23",
            "view_count": "279085",
            "thumbnail_url": "https://i.ytimg.com/vi/e6CGI5JOZ7g/hqdefault.jpg"
        },
        {
            "video_id": "oH1SFp-ZdlQ",
            "title": "유기사 무조건 녹아웃 1등하는 비결?! 팀나빠에게 복수하기 위해 단련했다!😱",
            "channel_name": "멜로우TV",
            "category": "Gaming",
            "duration": "15:02",
            "view_count": "75884",
            "thumbnail_url": "https://i.ytimg.com/vi/oH1SFp-ZdlQ/hqdefault.jpg"
        },
        {
            "video_id": "g1JlVmMEebI",
            "title": "SLAY (슬레이) '나타나 줘' Special Clip",
            "channel_name": "SLAY 슬레이 ",
            "category": "People & Blogs",
            "duration": "3:06",
            "view_count": "225073",
            "thumbnail_url": "https://i.ytimg.com/vi/g1JlVmMEebI/hqdefault.jpg"
        },
        {
            "video_id": "9428g3DyE7A",
            "title": "날 죽일 거면 목을 쳤어야지...",
            "channel_name": "김된모",
            "category": "Gaming",
            "duration": "17:35",
            "view_count": "94613",
            "thumbnail_url": "https://i.ytimg.com/vi/9428g3DyE7A/hqdefault.jpg"
        },
        {
            "video_id": "bhykDgIlX1Q",
            "title": "[스근한 발라드] ep.2 임가영(Im Ga Young)_그 밤 아래 우리 둘(Under the Same Night)",
            "channel_name": "1theK (원더케이)",
            "category": "Music",
            "duration": "3:43",
            "view_count": "192670",
            "thumbnail_url": "https://i.ytimg.com/vi/bhykDgIlX1Q/hqdefault.jpg"
        },
        {
            "video_id": "JPimg6RWDDU",
            "title": "리니지 클래식.. 서버 1등 데스나이트 먹었습니다 ㅎ",
            "channel_name": "겜케이",
            "category": "Gaming",
            "duration": "12:51",
            "view_count": "141002",
            "thumbnail_url": "https://i.ytimg.com/vi/JPimg6RWDDU/hqdefault.jpg"
        },
        {
            "video_id": "mUjAsuRKIDI",
            "title": "WATER",
            "channel_name": "ASH ISLAND - Topic",
            "category": "Music",
            "duration": "3:19",
            "view_count": "63400",
            "thumbnail_url": "https://i.ytimg.com/vi/mUjAsuRKIDI/hqdefault.jpg"
        },
        {
            "video_id": "4wzgO6Z-VKM",
            "title": "오징어맨",
            "channel_name": "괴물쥐 유튜브",
            "category": "Gaming",
            "duration": "20:20",
            "view_count": "445503",
            "thumbnail_url": "https://i.ytimg.com/vi/4wzgO6Z-VKM/hqdefault.jpg"
        },
        {
            "video_id": "S1bfg8s4OV8",
            "title": "Fashion",
            "channel_name": "IVE - Topic",
            "category": "Music",
            "duration": "2:09",
            "view_count": "214833",
            "thumbnail_url": "https://i.ytimg.com/vi/S1bfg8s4OV8/hqdefault.jpg"
        },
        {
            "video_id": "3IeOTXpTMkI",
            "title": "복구에 인생을 걸었습니다 [팡이요,  메이플스토리]",
            "channel_name": "팡이요",
            "category": "Gaming",
            "duration": "14:27",
            "view_count": "209818",
            "thumbnail_url": "https://i.ytimg.com/vi/3IeOTXpTMkI/hqdefault.jpg"
        },
        {
            "video_id": "FhGp3Q4ZXtk",
            "title": "[풀버전] 씨야 메인보컬 김연지 등장?!😮 라이브 실력에 난리 난 연습생들 반응ㄷㄷ🔥| 씨야 '미친 사랑의 노래' | SOONIGROUP",
            "channel_name": "SOONIGROUP [수니그룹]",
            "category": "Entertainment",
            "duration": "3:38",
            "view_count": "186439",
            "thumbnail_url": "https://i.ytimg.com/vi/FhGp3Q4ZXtk/hqdefault.jpg"
        },
        {
            "video_id": "WPVwoittibQ",
            "title": "더블 데이트",
            "channel_name": "PAKA",
            "category": "Gaming",
            "duration": "23:14",
            "view_count": "371117",
            "thumbnail_url": "https://i.ytimg.com/vi/WPVwoittibQ/hqdefault.jpg"
        },
        {
            "video_id": "pY4EbmZipsA",
            "title": "OKA (Prod. by CODE KUNST)",
            "channel_name": "MASON HOME - Topic",
            "category": "Music",
            "duration": "3:41",
            "view_count": "27819",
            "thumbnail_url": "https://i.ytimg.com/vi/pY4EbmZipsA/hqdefault.jpg"
        },
        {
            "video_id": "GSueJl9nk_Q",
            "title": "정말 닉값하시는군요",
            "channel_name": "왈도쿤",
            "category": "Gaming",
            "duration": "12:21",
            "view_count": "87075",
            "thumbnail_url": "https://i.ytimg.com/vi/GSueJl9nk_Q/hqdefault.jpg"
        },
        {
            "video_id": "wabwtySf8Xk",
            "title": "MSG (Prod. by Spatchies, PapZilla, KIRWAV, Sawat)",
            "channel_name": "MILLI - Topic",
            "category": "Music",
            "duration": "3:49",
            "view_count": "44632",
            "thumbnail_url": "https://i.ytimg.com/vi/wabwtySf8Xk/hqdefault.jpg"
        },
        {
            "video_id": "g4KzaXwNUEs",
            "title": "샤타포스로 1200억 날리고 열받아서 보조 강화 눌러버렸습니다",
            "channel_name": "글자네",
            "category": "Gaming",
            "duration": "19:09",
            "view_count": "75000",
            "thumbnail_url": "https://i.ytimg.com/vi/g4KzaXwNUEs/hqdefault.jpg"
        }
    ]
}